[
  {
    "file": "111901/113CIB318南港區玉成段303地號新建工程_評定書-1-12.html",
    "keywords": [
      "xff",
      "efa",
      "bc",
      "ee",
      "ba",
      "bb",
      "ca",
      "fc",
      "ae",
      "eba",
      "de",
      "cc",
      "cb",
      "ef",
      "tabc"
    ]
  },
  {
    "file": "111901/113CIB318南港區玉成段303地號新建工程_評定書-13-32.html",
    "keywords": [
      "xff",
      "bc",
      "cfb",
      "efa",
      "ba",
      "fd",
      "ca",
      "bb",
      "ef",
      "cd",
      "fee",
      "be",
      "fb",
      "eba",
      "dc"
    ]
  },
  {
    "file": "111901/113CIB318南港區玉成段303地號新建工程_評定書-33-69.html",
    "keywords": [
      "南港",
      "玉成",
      "新建",
      "工程",
      "cib",
      "南港區玉成段",
      "地號新建工程",
      "評定書",
      "fa",
      "aaa",
      "acb"
    ]
  },
  {
    "file": "111901/113CIB318南港區玉成段303地號新建工程_評定書-70-107.html",
    "keywords": [
      "xff",
      "ea",
      "cfb",
      "ee",
      "ba",
      "bc",
      "fd",
      "efa",
      "bb",
      "ef",
      "ad",
      "dda",
      "be",
      "fb",
      "ca"
    ]
  }
]